cnext_server/.gitignore
cnext_server/__init__.py
cnext_server/__main__.py
cnext_server/public/404.html
cnext_server/public/_next/static/chunks/269.befd1da30a34f25a.js
cnext_server/public/_next/static/chunks/2852872c-257ebc72a8902899.js
cnext_server/public/_next/static/chunks/325-3a16c76578325c87.js
cnext_server/public/_next/static/chunks/4ad82c5e-eacc478f45b94eba.js
cnext_server/public/_next/static/chunks/651.bfd69ea01d64d954.js
cnext_server/public/_next/static/chunks/660.2d01b32d8f282715.js
cnext_server/public/_next/static/chunks/741.25e0d543f796a94b.js
cnext_server/public/_next/static/chunks/75fc9c18-d4f616fecc6e1230.js
cnext_server/public/_next/static/chunks/866.f09fe9765cb7adf6.js
cnext_server/public/_next/static/chunks/e48519b3.c8db2bf231c5f0b8.js
cnext_server/public/_next/static/chunks/ed150ef9.8a701c53cbd4d124.js
cnext_server/public/_next/static/chunks/framework-0ba0ddd33199226d.js
cnext_server/public/_next/static/chunks/main-79e130091ee21132.js
cnext_server/public/_next/static/chunks/pages/_app-0e8b26db239a2114.js
cnext_server/public/_next/static/chunks/pages/_error-c13976a61913457b.js
cnext_server/public/_next/static/chunks/pages/index-7e5cf55cbd3ce6b5.js
cnext_server/public/_next/static/chunks/polyfills-c67a75d1b6f99dc8.js
cnext_server/public/_next/static/chunks/webpack-ac5cf69b96faa630.js
cnext_server/public/_next/static/css/713625ab96f56113.css
cnext_server/public/_next/static/css/f0abbfc8cca2b2f0.css
cnext_server/public/_next/static/hkK1rQiwVQdg9pTelDWN7/_buildManifest.js
cnext_server/public/_next/static/hkK1rQiwVQdg9pTelDWN7/_ssgManifest.js
cnext_server/public/favicon.ico
cnext_server/public/icons/cube-white.svg
cnext_server/public/icons/cube.svg
cnext_server/public/index.html
cnext_server/server/.dockerignore
cnext_server/server/build/config.gypi
cnext_server/server/Dockerfile
cnext_server/server/eventLog.js
cnext_server/server/ls/lsp_process.js
cnext_server/server/ls/streams.js
cnext_server/server/package-lock.json
cnext_server/server/package.json
cnext_test-0.7.5.dist-info/entry_points.txt
cnext_test-0.7.5.dist-info/WHEEL
cnext_test-0.7.5.dist-info/METADATA
cnext_test-0.7.5.dist-info/RECORD
